flatten_complex_json/Flatten_complex_json.py
flatten_complex_json/__init__.py
flatten_complex_json-0.0.4.dist-info/LICENCE
flatten_complex_json-0.0.4.dist-info/METADATA
flatten_complex_json-0.0.4.dist-info/WHEEL
flatten_complex_json-0.0.4.dist-info/top_level.txt
flatten_complex_json-0.0.4.dist-info/RECORD
