Metadata-Version: 2.1
Name: flatten-complex-json
Version: 0.0.4
Summary: Python Package to flatten the complex json data
Author: abhishek
Author-email: abhishekaggarwal1211@gmail.com
Keywords: flatten json,flatten api data,flat json data,python flatten dataframe,abhishek aggarwal
Classifier: Development Status :: 1 - Planning
Classifier: Intended Audience :: Developers
Classifier: Programming Language :: Python :: 3
Classifier: Operating System :: Unix
Classifier: Operating System :: MacOS :: MacOS X
Classifier: Operating System :: Microsoft :: Windows
License-File: LICENCE
